json_datetime_noamfisher/__init__.py
json_datetime_noamfisher/consts.py
json_datetime_noamfisher/decoder.py
json_datetime_noamfisher/encoder.py
json_datetime_noamfisher-1.0.dist-info/METADATA
json_datetime_noamfisher-1.0.dist-info/WHEEL
json_datetime_noamfisher-1.0.dist-info/top_level.txt
json_datetime_noamfisher-1.0.dist-info/RECORD
