Metadata-Version: 2.1
Name: json-datetime-noamfisher
Version: 1.0
Summary: allows you to dump / load jsons that contain date / datetime / time objects
Home-page: UNKNOWN
Author: Noam Fisher
Author-email: noam9997@gmail.com
License: UNKNOWN
Platform: UNKNOWN
Provides-Extra: test
Requires-Dist: pytest ; extra == 'test'
